{
  "code": "7.71.1",
  "module": "7",
  "moduleTitle": "Environmental performance - Climate change",
  "questionText": "Provide details of how your organization assesses the life cycle emissions of its products or services.",
  "questionKo": "제공 세부 정보 조직 배출량.",
  "questionType": "MATRIX",
  "mandatory": "False",
  "issueTags": "Climate Change",
  "sectorTags": "Capital goods",
  "simpleHelp": "To acquire an overall understanding of the total carbon impact of a product or service, it is necessary to assess emissions from the production process and use phase, but also emissions associated with the acquisition and disposal of the materials that make up the product. This question provides data users with information on your organization's approach to assessing product life cycle emissions, including the life cycle stages covered and the methodologies used.",
  "popupHelp": "",
  "baseOptions": [],
  "rows": [
    {
      "order": 1,
      "title": "Response row",
      "titleKo": "응답 행"
    }
  ],
  "columns": [
    {
      "code": "7.71.1.1",
      "text": "Products/services assessed",
      "type": "SINGLE_SELECT",
      "mandatory": "False",
      "options": [
        "All existing products/services",
        "All new products/services under development",
        "All existing and new products/services",
        "Representative selection of products/services",
        "On a case-by-case basis",
        "Products/services meeting certain criteria (please specify)"
      ],
      "simple_help": "",
      "popup_help": "",
      "textKo": "제품/서비스 평가된",
      "typeKo": "단일 선택",
      "mandatoryKo": "아니요",
      "optionsKo": [
        "모든 기존 제품/서비스",
        "모든 신규 제품/서비스 개발",
        "모든 기존 및 신규 제품/서비스",
        "선택 의 제품/서비스",
        "기준-",
        "제품/서비스 특정 기준 (직접 입력 명시)"
      ],
      "simple_helpKo": "",
      "popup_helpKo": ""
    },
    {
      "code": "7.71.1.2",
      "text": "Life cycle stage(s) most commonly covered",
      "type": "SINGLE_SELECT",
      "mandatory": "False",
      "options": [
        "Cradle-to-gate",
        "Cradle-to-grave",
        "Cradle-to-cradle/closed loop production",
        "Cradle-to-gate + end-of-life stage",
        "Gate-to-gate",
        "Use stage",
        "End-of-life stage",
        "Other, please specify"
      ],
      "simple_help": "",
      "popup_help": "",
      "textKo": "(s) 가장 포함된",
      "typeKo": "단일 선택",
      "mandatoryKo": "아니요",
      "optionsKo": [
        "- -",
        "- -",
        "/ 생산",
        "+ 의-",
        "- -",
        "사용",
        "의-",
        "기타, 직접 입력"
      ],
      "simple_helpKo": "",
      "popup_helpKo": ""
    },
    {
      "code": "7.71.1.3",
      "text": "Methodologies/standards/tools applied",
      "type": "MULTI_SELECT",
      "mandatory": "False",
      "options": [
        "Bilan Carbone",
        "EU Product Environmental Footprint (EUPEF)",
        "French Product Environmental Footprint",
        "GHG Protocol Product Accounting & Reporting Standard",
        "ISO 14025",
        "ISO 14040 & 14044",
        "ISO 14067",
        "PAS 2050",
        "Other, please specify"
      ],
      "simple_help": "Select all that apply:",
      "popup_help": "",
      "textKo": "방법론//도구",
      "typeKo": "복수 선택",
      "mandatoryKo": "아니요",
      "optionsKo": [
        "",
        "EU 환경 발자국 ()",
        "환경 발자국",
        "프로토콜 회계처리 & 보고 기준",
        "ISO 14025",
        "ISO 14040 & 14044",
        "ISO 14067",
        "2050",
        "기타, 직접 입력"
      ],
      "simple_helpKo": "선택 모든 적용:",
      "popup_helpKo": ""
    },
    {
      "code": "7.71.1.4",
      "text": "Comment",
      "type": "RICH_TEXT",
      "mandatory": "False",
      "options": [],
      "simple_help": "",
      "popup_help": "",
      "textKo": "의견",
      "typeKo": "서술형 입력",
      "mandatoryKo": "아니요",
      "optionsKo": [],
      "simple_helpKo": "",
      "popup_helpKo": ""
    }
  ],
  "guidance": [
    {
      "type": "Change From Last Year",
      "text": "No change",
      "typeKo": "전년 대비 변경사항",
      "textKo": "변경 없음"
    },
    {
      "type": "Question Dependencies",
      "text": "This question only appears if you select \"Yes\" in response to 7.71.",
      "typeKo": "문항 의존성",
      "textKo": "이 문항 만 표시됨 만약 귀사 선택 \"예\" 응답 7.71."
    },
    {
      "type": "Requested Content",
      "text": "General \nIt is acknowledged that your organization's approach to assessing the life cycle emissions of products or services may vary - please select the options that best describe your most common approach. \nProducts/services assessed (column 1) \nSelect the option that best describes your organization's approach to selecting products or services for assessment. If you wish to provide further details, you may do so in the \"Comment\" column.\nLife cycle stage(s) most commonly covered (column 2) \nSelect the life cycle stage(s) that you most commonly cover in your assessments. Refer to the explanation of terms below for definitions. \nComment (column 4) (optional) \nYou may use this column to provide further details of your organization's approach to assessing life cycle emissions.",
      "typeKo": "요청 내용",
      "textKo": "이 섹션은 해당 문항에서 CDP가 요청하는 작성 내용을 설명합니다. 위 응답방법, 열 구조, 드롭다운 선택지를 기준으로 보고연도와 조직 범위에 맞는 정보를 입력하십시오."
    },
    {
      "type": "Explanation of Terms",
      "text": "Gate-to-gate : The emissions and removals attributed to a studied product while it is under the ownership or control of the reporting company.\nCradle-to-gate : A partial life cycle assessment from material acquisition (cradle) through to when the product leaves the reporting company's gate (i.e. immediately following the product's production). Includes the material acquisition & pre-processing stage and the production stage.\nCradle-to-grave : A full life cycle assessment of emissions and removals attributed to a studied product from material acquisition through to the material or product end-of-life (grave). Includes the material acquisition & pre-processing stage, production stage, use stage and end-of-life stage.\nCradle-to-cradle/closed loop production : A full life cycle assessment from material acquisition though to end-of-life material or product recycling (i.e. cradle-to-grave + recycling). \nLife cycle stages (in line with the GHG Protocol Product Life Cycle Accounting and Reporting Standard ):\n- \nMaterial acquisition & pre-processing stage : A life cycle stage that begins when resources are extracted from nature and ends when the product components enter the gate of the studied product's production facility.\n-\nProduction stage : A life cycle stage that begins when the product components enter the production site for the studied product and ends when the finished studied product leaves the production gate.\n- \nUse stage : A life cycle stage that begins when the consumer takes possession of the product and ends when the used product is discarded.\n- \nEnd-of-life stage: A life cycle stage that begins when the used product is discarded by the consumer and ends when the product is returned to nature (e.g. incinerated) or allocated to another product's life cycle.",
      "typeKo": "용어 설명",
      "textKo": "이 섹션은 문항에서 사용하는 주요 용어의 의미를 설명합니다. 용어 해석은 CDP 2026 원문과 국문 양식의 용어 사용을 우선 적용하십시오."
    }
  ],
  "points": [
    {
      "sector": "Capital goods",
      "issue": "Climate change",
      "D": "3/3",
      "A": "1/1",
      "M": "1/1",
      "L": "1/1",
      "sectorKo": "자본재",
      "issueKo": "기후변화"
    }
  ],
  "criteria": [
    {
      "sector": "Capital goods",
      "issue": "Climate change",
      "level": "D",
      "criteria": "Points will be awarded per completed cell in proportion to the number of cells displayed.\nA maximum of 3/3 points is available for this question.",
      "sectorKo": "자본재",
      "issueKo": "기후변화",
      "levelKo": "D",
      "criteriaKo": "표시된 셀 수에 비례하여 완료된 셀마다 점수가 부여됩니다. 이 문항에서 최대 3/3점을 받을 수 있습니다."
    },
    {
      "sector": "Capital goods",
      "issue": "Climate change",
      "level": "A",
      "criteria": "Table completed - 1 point\nA maximum of 1/1 point is available for this question.",
      "sectorKo": "자본재",
      "issueKo": "기후변화",
      "levelKo": "A",
      "criteriaKo": "표 완료 - 1 점 이 문항에서 최대 1/1점을 받을 수 있습니다."
    },
    {
      "sector": "Capital goods",
      "issue": "Climate change",
      "level": "M",
      "criteria": "Full Awareness points must be awarded to be eligible for Management points.\nAll of the following met - 1 point\nAny of the following selected in column 'Products/services assessed':\n- 'All existing products/services'\n- 'All new products/services under development'\n- 'All existing and new products/services'\n- 'Representative selection of products/services'\nAND\nAny of the following selected in column 'Life cycle stage(s) most commonly covered'\n- 'Cradle-to-grave'\n- 'Cradle-to-cradle/closed loop production'\n- 'Cradle-to-gate + end-of-life stage'\n- 'Use stage'\nAND\nAny option excluding 'Other, please specify' selected in column 'Methodologies/standards/tools applied'.\nA maximum of 1/1 point is available for this question.",
      "sectorKo": "자본재",
      "issueKo": "기후변화",
      "levelKo": "M",
      "criteriaKo": "이 평가기준은 해당 점수 수준에서 요구되는 조건입니다. 배점표, 문항 응답 구조, 완료 셀, 선택지 및 설명 입력 여부를 함께 확인하십시오."
    },
    {
      "sector": "Capital goods",
      "issue": "Climate change",
      "level": "L",
      "criteria": "'All existing and new products/services' selected in column 'Products/services assessed' - 1 point\nA maximum of 1/1 point is available for this question.",
      "sectorKo": "자본재",
      "issueKo": "기후변화",
      "levelKo": "L",
      "criteriaKo": "'모든 기존 및 신규 제품/서비스' 열에서 선택 '제품/서비스 평가된' - 1 점 이 문항에서 최대 1/1점을 받을 수 있습니다."
    }
  ],
  "change": {
    "location": "Excel",
    "question_ko": "제공 세부 정보 조직 배출량.",
    "q2025": "Q7.71.1",
    "q2025_text": "Provide details of how your organization assesses the life cycle emissions of its products or services.",
    "change_status": "No change - 2026 source verified",
    "detail_change_types": "",
    "changed_question": false,
    "changed_response": false,
    "changed_options": false,
    "changed_guidance": false,
    "changed_scoring": false,
    "change_summary": "",
    "scoring_change_summary": "",
    "daml_summary": "Capital goods: D 3/3 | A 1/1 | M 1/1 | L 1/1",
    "reflected": "2026 question text applied\n2026 response type/columns applied\n2026 D/A/M/L point allocation linked\n2026 scoring criteria linked",
    "review_status": "변경 없음 확인 및 2026 원문 반영",
    "change_statusKo": "변경 없음 - 2026 원문 확인",
    "detail_change_typesKo": "",
    "change_summaryKo": "",
    "scoring_change_summaryKo": "",
    "daml_summaryKo": "자본재: D 3/3 | 1/1 | M 1/1 | L 1/1",
    "reflectedKo": "",
    "locationKo": "정량적",
    "locationEn": "Quantitative Excel",
    "review_statusKo": "변경 없음 및 2026 원천",
    "review_statusEn": "No change verified and 2026 source applied",
    "q2025_textKo": "제공 세부 정보 의 어떻게 귀사 배출량 의 그것의 제품 또는 서비스."
  },
  "defaultPoints": {
    "D": "3/3",
    "A": "1/1",
    "M": "1/1",
    "L": "1/1"
  },
  "sourceInfo": [
    {
      "name": "CDP Full Corporate Questionnaire and Reporting Guidance 2026",
      "version": "Released April 22, 2026",
      "nameKo": "CDP 2026 전체 기업 문항 및 보고 가이던스",
      "versionKo": "2026년 4월 22일 공개"
    },
    {
      "name": "CDP Questionnaire Changes Tracker 2026",
      "version": "Version 3, revised May 8, 2026",
      "nameKo": "CDP 2026 문항 변경 추적표",
      "versionKo": "버전 3, 2026년 5월 8일 개정"
    },
    {
      "name": "CDP Full Corporate Scoring Changes 2026",
      "version": "Released April 30, 2026",
      "nameKo": "CDP 2026 전체 기업 평가방법론 변경사항",
      "versionKo": "2026년 4월 30일 공개"
    },
    {
      "name": "CDP Climate Change Scoring Essential Criteria 2026",
      "version": "Released April 30, 2026",
      "nameKo": "CDP 2026 기후변화 평가 필수 기준",
      "versionKo": "2026년 4월 30일 공개"
    }
  ],
  "moduleTitleKo": "환경 성과 - 기후 변경",
  "questionTypeKo": "표 형식 응답",
  "mandatoryKo": "아니요",
  "issueTagsKo": "기후 변경",
  "sectorTagsKo": "자본재",
  "simpleHelpKo": "이 문항은 '제공 세부 정보 조직 배출량.'에 대한 배경 설명입니다. CDP 응답자는 보고연도 기준으로 조직의 환경 관련 현황, 리스크, 기회, 성과 또는 관리체계를 문항의 응답 구조에 맞춰 설명해야 합니다.",
  "popupHelpKo": "",
  "baseOptionsKo": [],
  "translationSourceKo": "2025 CDP 국문 양식 및 2026 CDP 원문 기준 국문 보정"
}
